custom_cache/__init__.py
custom_cache/async_custom_cache.py
custom_cache/async_utils.py
custom_cache/custom_cache.py
custom_cache/decorators.py
custom_cache/key_builder.py
custom_cache/py.typed
custom_cache/redis_mixins.py
custom_cache/utils.py
relaycache-0.1.1.dist-info/METADATA
relaycache-0.1.1.dist-info/WHEEL
relaycache-0.1.1.dist-info/top_level.txt
relaycache-0.1.1.dist-info/RECORD
