Metadata-Version: 2.4
Name: relaycache
Version: 0.1.1
Summary: Universal caching library with sync/async support, tagging, singleflight and distributed locks
Author-email: Potrebchuk Oleg <potrebchuk0@gmail.com>
Project-URL: Homepage, https://github.com/AIMERPRO/relaycache
Project-URL: Documentation, https://github.com/AIMERPRO/relaycache#readme
Project-URL: Repository, https://github.com/AIMERPRO/relaycache
Project-URL: Bug Tracker, https://github.com/AIMERPRO/relaycache/issues
Keywords: cache,redis,async,singleflight,tagging,distributed,python
Classifier: Development Status :: 4 - Beta
Classifier: Intended Audience :: Developers
Classifier: License :: OSI Approved :: MIT License
Classifier: Operating System :: OS Independent
Classifier: Programming Language :: Python :: 3
Classifier: Programming Language :: Python :: 3.8
Classifier: Programming Language :: Python :: 3.9
Classifier: Programming Language :: Python :: 3.10
Classifier: Programming Language :: Python :: 3.11
Classifier: Programming Language :: Python :: 3.12
Classifier: Topic :: Software Development :: Libraries :: Python Modules
Classifier: Topic :: Database
Classifier: Topic :: System :: Distributed Computing
Classifier: Framework :: AsyncIO
Requires-Python: >=3.8
Requires-Dist: redis>=4.0.0
Provides-Extra: dev
Requires-Dist: pytest>=7.0.0; extra == "dev"
Requires-Dist: pytest-asyncio>=0.21.0; extra == "dev"
Requires-Dist: redis>=4.0.0; extra == "dev"
Provides-Extra: aioredis
Requires-Dist: aioredis>=2.0.0; extra == "aioredis"
